Metadata-Version: 1.0
Name: gitclassroom
Version: 0.1
Summary: Package supports auto-marking student's assignment on GitHub
Home-page: https://github.com/TrCaM/1406-github
Author: Tri Cao
Author-email: cmthscb@gmail.com
License: MIT
Platform: UNKNOWN
